{
  "version": "v114-region-search-places",
  "updated": "2026-04-28",
  "purpose": "Справочник населённых пунктов, которые используются только как поисковые алиасы к обзорным страницам регионов. Не является отдельным природно-климатическим районированием.",
  "minimumPerRegion": 15,
  "settlementCount": 1334,
  "aliases": {
    "belgorodskaya-oblast": [
      "Белгород",
      "Старый Оскол",
      "Губкин",
      "Шебекино",
      "Алексеевка",
      "Валуйки",
      "Строитель",
      "Новый Оскол",
      "Бирюч",
      "Грайворон",
      "Короча",
      "Борисовка",
      "Чернянка",
      "Ровеньки",
      "Прохоровка",
      "Ивня"
    ],
    "bryanskaya-oblast": [
      "Брянск",
      "Клинцы",
      "Новозыбков",
      "Дятьково",
      "Унеча",
      "Стародуб",
      "Карачев",
      "Жуковка",
      "Сельцо",
      "Почеп",
      "Трубчевск",
      "Фокино",
      "Сураж",
      "Мглин",
      "Севск",
      "Злынка"
    ],
    "vladimirskaya-oblast": [
      "Владимир",
      "Ковров",
      "Муром",
      "Александров",
      "Гусь-Хрустальный",
      "Кольчугино",
      "Вязники",
      "Киржач",
      "Юрьев-Польский",
      "Радужный",
      "Собинка",
      "Покров",
      "Лакинск",
      "Меленки",
      "Камешково",
      "Суздаль"
    ],
    "voronezhskaya-oblast": [
      "Воронеж",
      "Борисоглебск",
      "Россошь",
      "Лиски",
      "Острогожск",
      "Нововоронеж",
      "Семилуки",
      "Павловск",
      "Бутурлиновка",
      "Калач",
      "Поворино",
      "Богучар",
      "Эртиль",
      "Новохопёрск",
      "Бобров",
      "Анна"
    ],
    "ivanovskaya-oblast": [
      "Иваново",
      "Кинешма",
      "Шуя",
      "Вичуга",
      "Фурманов",
      "Тейково",
      "Родники",
      "Кохма",
      "Приволжск",
      "Южа",
      "Заволжск",
      "Наволоки",
      "Комсомольск",
      "Юрьевец",
      "Пучеж",
      "Гаврилов Посад"
    ],
    "kaluzhskaya-oblast": [
      "Калуга",
      "Обнинск",
      "Людиново",
      "Киров",
      "Малоярославец",
      "Балабаново",
      "Козельск",
      "Сухиничи",
      "Кондрово",
      "Жуков",
      "Боровск",
      "Кремёнки",
      "Ермолино",
      "Таруса",
      "Медынь",
      "Мещовск"
    ],
    "kostromskaya-oblast": [
      "Кострома",
      "Буй",
      "Шарья",
      "Нерехта",
      "Галич",
      "Мантурово",
      "Волгореченск",
      "Нея",
      "Макарьев",
      "Солигалич",
      "Чухлома",
      "Кологрив",
      "Красное-на-Волге",
      "Судиславль",
      "Поназырево",
      "Вохма"
    ],
    "kurskaya-oblast": [
      "Курск",
      "Железногорск",
      "Курчатов",
      "Льгов",
      "Рыльск",
      "Щигры",
      "Обоянь",
      "Дмитриев",
      "Фатеж",
      "Суджа",
      "Золотухино",
      "Тим",
      "Медвенка",
      "Глушково",
      "Касторное",
      "Поныри"
    ],
    "lipetskaya-oblast": [
      "Липецк",
      "Елец",
      "Грязи",
      "Лебедянь",
      "Данков",
      "Усмань",
      "Чаплыгин",
      "Задонск",
      "Тербуны",
      "Добринка",
      "Доброе",
      "Хлевное",
      "Становое",
      "Измалково",
      "Лев Толстой",
      "Волово"
    ],
    "moskovskaya-oblast": [
      "Балашиха",
      "Подольск",
      "Химки",
      "Мытищи",
      "Королёв",
      "Люберцы",
      "Красногорск",
      "Электросталь",
      "Коломна",
      "Одинцово",
      "Сергиев Посад",
      "Щёлково",
      "Домодедово",
      "Раменское",
      "Орехово-Зуево",
      "Долгопрудный",
      "Пушкино",
      "Реутов",
      "Жуковский",
      "Ногинск"
    ],
    "moskva": [
      "Москва",
      "Зеленоград",
      "Троицк",
      "Щербинка",
      "Московский",
      "Коммунарка",
      "Внуково",
      "Кокошкино",
      "Киевский",
      "Вороново",
      "Краснопахорское",
      "Роговское",
      "Марушкинское",
      "Первомайское",
      "Сосенское",
      "Новофёдоровское"
    ],
    "orlovskaya-oblast": [
      "Орёл",
      "Ливны",
      "Мценск",
      "Болхов",
      "Дмитровск",
      "Малоархангельск",
      "Новосиль",
      "Кромы",
      "Знаменское",
      "Хотынец",
      "Верховье",
      "Глазуновка",
      "Долгое",
      "Колпна",
      "Покровское",
      "Залегощь"
    ],
    "ryazanskaya-oblast": [
      "Рязань",
      "Касимов",
      "Скопин",
      "Сасово",
      "Ряжск",
      "Рыбное",
      "Новомичуринск",
      "Кораблино",
      "Михайлов",
      "Спасск-Рязанский",
      "Шацк",
      "Спас-Клепики",
      "Старожилово",
      "Пронск",
      "Сараи",
      "Милославское"
    ],
    "smolenskaya-oblast": [
      "Смоленск",
      "Вязьма",
      "Рославль",
      "Ярцево",
      "Сафоново",
      "Гагарин",
      "Десногорск",
      "Дорогобуж",
      "Рудня",
      "Ельня",
      "Починок",
      "Сычёвка",
      "Велиж",
      "Демидов",
      "Духовщина",
      "Красный"
    ],
    "tambovskaya-oblast": [
      "Тамбов",
      "Мичуринск",
      "Рассказово",
      "Моршанск",
      "Котовск",
      "Уварово",
      "Кирсанов",
      "Жердевка",
      "Первомайский",
      "Сосновка",
      "Знаменка",
      "Инжавино",
      "Мучкапский",
      "Петровское",
      "Сампур",
      "Пичаево"
    ],
    "tverskaya-oblast": [
      "Тверь",
      "Ржев",
      "Вышний Волочёк",
      "Торжок",
      "Кимры",
      "Конаково",
      "Удомля",
      "Бологое",
      "Осташков",
      "Кашин",
      "Калязин",
      "Лихославль",
      "Нелидово",
      "Старица",
      "Зубцов",
      "Бежецк"
    ],
    "tulskaya-oblast": [
      "Тула",
      "Новомосковск",
      "Донской",
      "Алексин",
      "Щёкино",
      "Узловая",
      "Ефремов",
      "Богородицк",
      "Кимовск",
      "Киреевск",
      "Суворов",
      "Ясногорск",
      "Венёв",
      "Белёв",
      "Плавск",
      "Липки"
    ],
    "yaroslavskaya-oblast": [
      "Ярославль",
      "Рыбинск",
      "Тутаев",
      "Переславль-Залесский",
      "Углич",
      "Ростов",
      "Гаврилов-Ям",
      "Данилов",
      "Пошехонье",
      "Мышкин",
      "Любим",
      "Борисоглебский",
      "Некрасовское",
      "Семибратово",
      "Петровское",
      "Константиновский"
    ],
    "respublika-kareliya": [
      "Петрозаводск",
      "Кондопога",
      "Костомукша",
      "Сегежа",
      "Сортавала",
      "Медвежьегорск",
      "Беломорск",
      "Кемь",
      "Питкяранта",
      "Олонец",
      "Лахденпохья",
      "Суоярви",
      "Пудож",
      "Надвоицы",
      "Пряжа",
      "Калевала"
    ],
    "respublika-komi": [
      "Сыктывкар",
      "Ухта",
      "Воркута",
      "Печора",
      "Усинск",
      "Инта",
      "Сосногорск",
      "Емва",
      "Микунь",
      "Вуктыл",
      "Жешарт",
      "Выльгорт",
      "Айкино",
      "Усть-Кулом",
      "Объячево",
      "Троицко-Печорск"
    ],
    "arhangelskaya-oblast": [
      "Архангельск",
      "Северодвинск",
      "Котлас",
      "Новодвинск",
      "Коряжма",
      "Мирный",
      "Вельск",
      "Няндома",
      "Онега",
      "Каргополь",
      "Шенкурск",
      "Мезень",
      "Сольвычегодск",
      "Холмогоры",
      "Плесецк",
      "Савинский"
    ],
    "nenetskiy-avtonomnyy-okrug": [
      "Нарьян-Мар",
      "Искателей",
      "Красное",
      "Нельмин-Нос",
      "Тельвиска",
      "Оксино",
      "Харута",
      "Хорей-Вер",
      "Несь",
      "Ома",
      "Индига",
      "Амдерма",
      "Варандей",
      "Бугрино",
      "Усть-Кара",
      "Коткино"
    ],
    "vologodskaya-oblast": [
      "Вологда",
      "Череповец",
      "Сокол",
      "Великий Устюг",
      "Грязовец",
      "Бабаево",
      "Вытегра",
      "Тотьма",
      "Харовск",
      "Белозерск",
      "Устюжна",
      "Никольск",
      "Кириллов",
      "Кадников",
      "Чагода",
      "Шексна"
    ],
    "kaliningradskaya-oblast": [
      "Калининград",
      "Советск",
      "Черняховск",
      "Балтийск",
      "Гусев",
      "Светлый",
      "Гурьевск",
      "Зеленоградск",
      "Пионерский",
      "Неман",
      "Светлогорск",
      "Мамоново",
      "Полесск",
      "Багратионовск",
      "Гвардейск",
      "Озёрск"
    ],
    "leningradskaya-oblast": [
      "Гатчина",
      "Выборг",
      "Всеволожск",
      "Сосновый Бор",
      "Тихвин",
      "Кириши",
      "Кингисепп",
      "Луга",
      "Волхов",
      "Тосно",
      "Сланцы",
      "Кировск",
      "Отрадное",
      "Пикалёво",
      "Сертолово",
      "Приозерск"
    ],
    "murmanskaya-oblast": [
      "Мурманск",
      "Апатиты",
      "Североморск",
      "Мончегорск",
      "Кандалакша",
      "Кировск",
      "Оленегорск",
      "Полярный",
      "Ковдор",
      "Заполярный",
      "Полярные Зори",
      "Кола",
      "Заозёрск",
      "Снежногорск",
      "Гаджиево",
      "Видяево"
    ],
    "novgorodskaya-oblast": [
      "Великий Новгород",
      "Боровичи",
      "Старая Русса",
      "Пестово",
      "Валдай",
      "Чудово",
      "Окуловка",
      "Малая Вишера",
      "Сольцы",
      "Холм",
      "Крестцы",
      "Демянск",
      "Парфино",
      "Шимск",
      "Батецкий",
      "Хвойная"
    ],
    "pskovskaya-oblast": [
      "Псков",
      "Великие Луки",
      "Остров",
      "Невель",
      "Опочка",
      "Печоры",
      "Порхов",
      "Дно",
      "Новосокольники",
      "Себеж",
      "Гдов",
      "Пустошка",
      "Пыталово",
      "Плюсса",
      "Струги Красные",
      "Бежаницы"
    ],
    "sankt-peterburg": [
      "Санкт-Петербург",
      "Колпино",
      "Пушкин",
      "Петергоф",
      "Кронштадт",
      "Ломоносов",
      "Павловск",
      "Сестрорецк",
      "Зеленогорск",
      "Красное Село",
      "Стрельна",
      "Парголово",
      "Левашово",
      "Металлострой",
      "Песочный",
      "Шушары",
      "Лисий Нос"
    ],
    "respublika-adygeya": [
      "Майкоп",
      "Адыгейск",
      "Яблоновский",
      "Энем",
      "Тлюстенхабль",
      "Красногвардейское",
      "Гиагинская",
      "Кошехабль",
      "Ханская",
      "Дондуковская",
      "Тульский",
      "Каменномостский",
      "Гузерипль",
      "Хакуринохабль",
      "Шовгеновский",
      "Понежукай"
    ],
    "respublika-kalmykiya": [
      "Элиста",
      "Лагань",
      "Городовиковск",
      "Малые Дербеты",
      "Яшалта",
      "Яшкуль",
      "Ики-Бурул",
      "Комсомольский",
      "Троицкое",
      "Садовое",
      "Приютное",
      "Цаган Аман",
      "Большой Царын",
      "Кетченеры",
      "Утта",
      "Артезиан"
    ],
    "krasnodarskiy-kray": [
      "Краснодар",
      "Сочи",
      "Новороссийск",
      "Армавир",
      "Ейск",
      "Анапа",
      "Геленджик",
      "Туапсе",
      "Тихорецк",
      "Кропоткин",
      "Славянск-на-Кубани",
      "Лабинск",
      "Тимашёвск",
      "Крымск",
      "Апшеронск",
      "Белореченск"
    ],
    "astrahanskaya-oblast": [
      "Астрахань",
      "Ахтубинск",
      "Знаменск",
      "Харабали",
      "Камызяк",
      "Нариманов",
      "Красный Яр",
      "Икряное",
      "Лиман",
      "Енотаевка",
      "Володарский",
      "Началово",
      "Чёрный Яр",
      "Капустин Яр",
      "Верхний Баскунчак",
      "Красные Баррикады"
    ],
    "volgogradskaya-oblast": [
      "Волгоград",
      "Волжский",
      "Камышин",
      "Михайловка",
      "Урюпинск",
      "Фролово",
      "Калач-на-Дону",
      "Котельниково",
      "Суровикино",
      "Котово",
      "Жирновск",
      "Палласовка",
      "Дубовка",
      "Ленинск",
      "Николаевск",
      "Быково"
    ],
    "rostovskaya-oblast": [
      "Ростов-на-Дону",
      "Таганрог",
      "Шахты",
      "Волгодонск",
      "Новочеркасск",
      "Батайск",
      "Новошахтинск",
      "Каменск-Шахтинский",
      "Азов",
      "Гуково",
      "Сальск",
      "Донецк",
      "Белая Калитва",
      "Аксай",
      "Миллерово",
      "Морозовск"
    ],
    "respublika-dagestan": [
      "Махачкала",
      "Хасавюрт",
      "Дербент",
      "Каспийск",
      "Буйнакск",
      "Избербаш",
      "Кизляр",
      "Кизилюрт",
      "Дагестанские Огни",
      "Южно-Сухокумск",
      "Бабаюрт",
      "Карабудахкент",
      "Тарки",
      "Ахты",
      "Ботлих",
      "Гуниб"
    ],
    "respublika-ingushetiya": [
      "Назрань",
      "Магас",
      "Сунжа",
      "Малгобек",
      "Карабулак",
      "Экажево",
      "Плиево",
      "Кантышево",
      "Барсуки",
      "Сагопши",
      "Нестеровская",
      "Орджоникидзевская",
      "Галашки",
      "Джейрах",
      "Троицкая",
      "Али-Юрт"
    ],
    "kabardino-balkarskaya-respublika": [
      "Нальчик",
      "Прохладный",
      "Баксан",
      "Нарткала",
      "Майский",
      "Терек",
      "Тырныауз",
      "Чегем",
      "Залукокоаже",
      "Кашхатау",
      "Анзорей",
      "Урвань",
      "Кенже",
      "Исламей",
      "Эльбрус",
      "Верхняя Балкария"
    ],
    "karachaevo-cherkesskaya-respublika": [
      "Черкесск",
      "Усть-Джегута",
      "Карачаевск",
      "Теберда",
      "Зеленчукская",
      "Эркен-Шахар",
      "Адыге-Хабль",
      "Хабез",
      "Учкекен",
      "Курджиново",
      "Домбай",
      "Преградная",
      "Исправная",
      "Красный Курган",
      "Медногорский",
      "Орджоникидзевский"
    ],
    "respublika-severnaya-osetiya-alaniya": [
      "Владикавказ",
      "Моздок",
      "Беслан",
      "Алагир",
      "Ардон",
      "Дигора",
      "Эльхотово",
      "Чикола",
      "Октябрьское",
      "Михайловское",
      "Заводской",
      "Гизель",
      "Верхний Фиагдон",
      "Фиагдон",
      "Архонская",
      "Ногир"
    ],
    "chechenskaya-respublika": [
      "Грозный",
      "Урус-Мартан",
      "Шали",
      "Гудермес",
      "Аргун",
      "Курчалой",
      "Ачхой-Мартан",
      "Наурская",
      "Шатой",
      "Итум-Кали",
      "Ведено",
      "Серноводское",
      "Толстой-Юрт",
      "Аллерой",
      "Автуры",
      "Цоцин-Юрт"
    ],
    "stavropolskiy-kray": [
      "Ставрополь",
      "Пятигорск",
      "Кисловодск",
      "Ессентуки",
      "Невинномысск",
      "Минеральные Воды",
      "Георгиевск",
      "Михайловск",
      "Будённовск",
      "Изобильный",
      "Светлоград",
      "Благодарный",
      "Зеленокумск",
      "Нефтекумск",
      "Ипатово",
      "Новоалександровск"
    ],
    "bashkortostan": [
      "Уфа",
      "Стерлитамак",
      "Салават",
      "Нефтекамск",
      "Октябрьский",
      "Туймазы",
      "Белорецк",
      "Ишимбай",
      "Сибай",
      "Кумертау",
      "Белебей",
      "Мелеуз",
      "Бирск",
      "Учалы",
      "Дюртюли",
      "Янаул"
    ],
    "respublika-mariy-el": [
      "Йошкар-Ола",
      "Волжск",
      "Козьмодемьянск",
      "Звенигово",
      "Медведево",
      "Морки",
      "Сернур",
      "Советский",
      "Оршанка",
      "Новый Торъял",
      "Килемары",
      "Параньга",
      "Мари-Турек",
      "Юрино",
      "Красногорский",
      "Суслонгер"
    ],
    "respublika-mordoviya": [
      "Саранск",
      "Рузаевка",
      "Ковылкино",
      "Краснослободск",
      "Ардатов",
      "Темников",
      "Инсар",
      "Лямбирь",
      "Торбеево",
      "Зубова Поляна",
      "Ромоданово",
      "Чамзинка",
      "Комсомольский",
      "Атяшево",
      "Большое Игнатово",
      "Старое Шайгово"
    ],
    "respublika-tatarstan": [
      "Казань",
      "Набережные Челны",
      "Нижнекамск",
      "Альметьевск",
      "Зеленодольск",
      "Бугульма",
      "Елабуга",
      "Лениногорск",
      "Чистополь",
      "Заинск",
      "Азнакаево",
      "Нурлат",
      "Бавлы",
      "Менделеевск",
      "Буинск",
      "Арск"
    ],
    "udmurtskaya-respublika": [
      "Ижевск",
      "Воткинск",
      "Сарапул",
      "Глазов",
      "Можга",
      "Камбарка",
      "Ува",
      "Игра",
      "Балезино",
      "Завьялово",
      "Малая Пурга",
      "Алнаши",
      "Кез",
      "Шаркан",
      "Якшур-Бодья",
      "Кизнер"
    ],
    "chuvashskaya-respublika": [
      "Чебоксары",
      "Новочебоксарск",
      "Канаш",
      "Алатырь",
      "Шумерля",
      "Цивильск",
      "Козловка",
      "Мариинский Посад",
      "Ядрин",
      "Урмары",
      "Батырево",
      "Комсомольское",
      "Ибреси",
      "Красноармейское",
      "Вурнары",
      "Порецкое"
    ],
    "permskiy-kray": [
      "Пермь",
      "Березники",
      "Соликамск",
      "Чайковский",
      "Кунгур",
      "Лысьва",
      "Краснокамск",
      "Чусовой",
      "Добрянка",
      "Чернушка",
      "Кудымкар",
      "Губаха",
      "Верещагино",
      "Оса",
      "Нытва",
      "Александровск"
    ],
    "kirovskaya-oblast": [
      "Киров",
      "Кирово-Чепецк",
      "Слободской",
      "Вятские Поляны",
      "Котельнич",
      "Омутнинск",
      "Яранск",
      "Советск",
      "Сосновка",
      "Белая Холуница",
      "Луза",
      "Зуевка",
      "Нолинск",
      "Уржум",
      "Малмыж",
      "Мураши"
    ],
    "nizhegorodskaya-oblast": [
      "Нижний Новгород",
      "Дзержинск",
      "Арзамас",
      "Саров",
      "Бор",
      "Кстово",
      "Павлово",
      "Выкса",
      "Балахна",
      "Заволжье",
      "Богородск",
      "Кулебаки",
      "Городец",
      "Семёнов",
      "Лысково",
      "Сергач"
    ],
    "orenburgskaya-oblast": [
      "Оренбург",
      "Орск",
      "Новотроицк",
      "Бузулук",
      "Бугуруслан",
      "Гай",
      "Сорочинск",
      "Соль-Илецк",
      "Медногорск",
      "Кувандык",
      "Абдулино",
      "Ясный",
      "Акбулак",
      "Саракташ",
      "Домбаровский",
      "Переволоцкий"
    ],
    "penzenskaya-oblast": [
      "Пенза",
      "Кузнецк",
      "Заречный",
      "Каменка",
      "Сердобск",
      "Нижний Ломов",
      "Никольск",
      "Городище",
      "Белинский",
      "Спасск",
      "Сурск",
      "Мокшан",
      "Бессоновка",
      "Башмаково",
      "Исса",
      "Колышлей"
    ],
    "samarskaya-oblast": [
      "Самара",
      "Тольятти",
      "Сызрань",
      "Новокуйбышевск",
      "Чапаевск",
      "Жигулёвск",
      "Отрадный",
      "Кинель",
      "Похвистнево",
      "Октябрьск",
      "Нефтегорск",
      "Безенчук",
      "Алексеевка",
      "Красный Яр",
      "Большая Черниговка",
      "Елховка"
    ],
    "saratovskaya-oblast": [
      "Саратов",
      "Энгельс",
      "Балаково",
      "Балашов",
      "Вольск",
      "Пугачёв",
      "Ртищево",
      "Маркс",
      "Петровск",
      "Аткарск",
      "Красноармейск",
      "Ершов",
      "Новоузенск",
      "Калининск",
      "Хвалынск",
      "Красный Кут"
    ],
    "ulyanovskaya-oblast": [
      "Ульяновск",
      "Димитровград",
      "Инза",
      "Барыш",
      "Новоульяновск",
      "Сенгилей",
      "Карсун",
      "Новоспасское",
      "Чердаклы",
      "Николаевка",
      "Павловка",
      "Тереньга",
      "Сурское",
      "Цильна",
      "Большое Нагаткино",
      "Мулловка"
    ],
    "kurganskaya-oblast": [
      "Курган",
      "Шадринск",
      "Шумиха",
      "Куртамыш",
      "Катайск",
      "Далматово",
      "Петухово",
      "Макушино",
      "Щучье",
      "Каргаполье",
      "Варгаши",
      "Кетово",
      "Мишкино",
      "Целинное",
      "Лебяжье",
      "Половинное"
    ],
    "sverdlovskaya-oblast": [
      "Екатеринбург",
      "Нижний Тагил",
      "Каменск-Уральский",
      "Первоуральск",
      "Серов",
      "Новоуральск",
      "Верхняя Пышма",
      "Асбест",
      "Ревда",
      "Полевской",
      "Краснотурьинск",
      "Лесной",
      "Верхняя Салда",
      "Качканар",
      "Ирбит",
      "Красноуфимск"
    ],
    "tyumenskaya-oblast": [
      "Тюмень",
      "Тобольск",
      "Ишим",
      "Ялуторовск",
      "Заводоуковск",
      "Голышманово",
      "Омутинское",
      "Винзили",
      "Боровский",
      "Богандинский",
      "Уват",
      "Ярково",
      "Абатское",
      "Викулово",
      "Исетское",
      "Казанское"
    ],
    "chelyabinskaya-oblast": [
      "Челябинск",
      "Магнитогорск",
      "Златоуст",
      "Миасс",
      "Копейск",
      "Озёрск",
      "Троицк",
      "Снежинск",
      "Сатка",
      "Чебаркуль",
      "Кыштым",
      "Южноуральск",
      "Коркино",
      "Еманжелинск",
      "Касли",
      "Верхний Уфалей"
    ],
    "hanty-mansiyskiy-avtonomnyy-okrug-yugra": [
      "Сургут",
      "Нижневартовск",
      "Нефтеюганск",
      "Ханты-Мансийск",
      "Когалым",
      "Нягань",
      "Мегион",
      "Лангепас",
      "Радужный",
      "Урай",
      "Лянтор",
      "Пыть-Ях",
      "Югорск",
      "Советский",
      "Белоярский",
      "Покачи"
    ],
    "yamalo-nenetskiy-avtonomnyy-okrug": [
      "Новый Уренгой",
      "Ноябрьск",
      "Салехард",
      "Надым",
      "Муравленко",
      "Губкинский",
      "Лабытнанги",
      "Тарко-Сале",
      "Аксарка",
      "Харп",
      "Пангоды",
      "Уренгой",
      "Пурпе",
      "Коротчаево",
      "Сабетта",
      "Новый Порт"
    ],
    "respublika-altay": [
      "Горно-Алтайск",
      "Майма",
      "Кош-Агач",
      "Турочак",
      "Чемал",
      "Онгудай",
      "Усть-Кан",
      "Усть-Кокса",
      "Шебалино",
      "Чоя",
      "Улаган",
      "Акташ",
      "Кызыл-Озек",
      "Манжерок",
      "Иогач",
      "Артыбаш"
    ],
    "respublika-tyva": [
      "Кызыл",
      "Ак-Довурак",
      "Шагонар",
      "Чадан",
      "Туран",
      "Бай-Хаак",
      "Сарыг-Сеп",
      "Каа-Хем",
      "Эрзин",
      "Хову-Аксы",
      "Суг-Аксы",
      "Кызыл-Мажалык",
      "Мугур-Аксы",
      "Самагалтай",
      "Тээли",
      "Тоора-Хем"
    ],
    "respublika-hakasiya": [
      "Абакан",
      "Черногорск",
      "Саяногорск",
      "Абаза",
      "Сорск",
      "Усть-Абакан",
      "Шира",
      "Белый Яр",
      "Аскиз",
      "Таштып",
      "Бея",
      "Копьёво",
      "Коммунар",
      "Пригорск",
      "Майна",
      "Черёмушки"
    ],
    "altayskiy-kray": [
      "Барнаул",
      "Бийск",
      "Рубцовск",
      "Новоалтайск",
      "Заринск",
      "Камень-на-Оби",
      "Славгород",
      "Алейск",
      "Яровое",
      "Белокуриха",
      "Горняк",
      "Змеиногорск",
      "Павловск",
      "Тальменка",
      "Кулунда",
      "Ребриха"
    ],
    "krasnoyarskiy-kray": [
      "Красноярск",
      "Норильск",
      "Ачинск",
      "Канск",
      "Железногорск",
      "Минусинск",
      "Зеленогорск",
      "Лесосибирск",
      "Назарово",
      "Шарыпово",
      "Дивногорск",
      "Сосновоборск",
      "Енисейск",
      "Боготол",
      "Иланский",
      "Ужур"
    ],
    "irkutskaya-oblast": [
      "Иркутск",
      "Братск",
      "Ангарск",
      "Усть-Илимск",
      "Усолье-Сибирское",
      "Черемхово",
      "Шелехов",
      "Усть-Кут",
      "Тулун",
      "Саянск",
      "Нижнеудинск",
      "Тайшет",
      "Вихоревка",
      "Зима",
      "Железногорск-Илимский",
      "Байкальск"
    ],
    "kemerovskaya-oblast-kuzbass": [
      "Кемерово",
      "Новокузнецк",
      "Прокопьевск",
      "Междуреченск",
      "Ленинск-Кузнецкий",
      "Киселёвск",
      "Юрга",
      "Белово",
      "Анжеро-Судженск",
      "Осинники",
      "Мыски",
      "Мариинск",
      "Топки",
      "Таштагол",
      "Калтан",
      "Берёзовский"
    ],
    "novosibirskaya-oblast": [
      "Новосибирск",
      "Бердск",
      "Искитим",
      "Куйбышев",
      "Барабинск",
      "Карасук",
      "Обь",
      "Татарск",
      "Тогучин",
      "Черепаново",
      "Болотное",
      "Купино",
      "Чулым",
      "Колывань",
      "Ордынское",
      "Краснообск"
    ],
    "omskaya-oblast": [
      "Омск",
      "Тара",
      "Калачинск",
      "Исилькуль",
      "Называевск",
      "Тюкалинск",
      "Любинский",
      "Черлак",
      "Большеречье",
      "Муромцево",
      "Таврическое",
      "Русская Поляна",
      "Павлоградка",
      "Москаленки",
      "Марьяновка",
      "Азово"
    ],
    "tomskaya-oblast": [
      "Томск",
      "Северск",
      "Стрежевой",
      "Асино",
      "Колпашево",
      "Кедровый",
      "Каргасок",
      "Мельниково",
      "Тегульдет",
      "Парабель",
      "Белый Яр",
      "Молчаново",
      "Кожевниково",
      "Подгорное",
      "Первомайское",
      "Зырянское"
    ],
    "respublika-buryatiya": [
      "Улан-Удэ",
      "Северобайкальск",
      "Кяхта",
      "Гусиноозёрск",
      "Закаменск",
      "Бабушкин",
      "Таксимо",
      "Селенгинск",
      "Онохой",
      "Каменск",
      "Хоринск",
      "Мухоршибирь",
      "Курумкан",
      "Баргузин",
      "Турунтаево",
      "Кабанск"
    ],
    "respublika-saha-yakutiya": [
      "Якутск",
      "Нерюнгри",
      "Мирный",
      "Ленск",
      "Алдан",
      "Удачный",
      "Вилюйск",
      "Нюрба",
      "Покровск",
      "Олёкминск",
      "Томмот",
      "Среднеколымск",
      "Верхоянск",
      "Тикси",
      "Черский",
      "Жатай"
    ],
    "zabaykalskiy-kray": [
      "Чита",
      "Краснокаменск",
      "Борзя",
      "Петровск-Забайкальский",
      "Нерчинск",
      "Могоча",
      "Шилка",
      "Балей",
      "Хилок",
      "Сретенск",
      "Карымское",
      "Агинское",
      "Забайкальск",
      "Чернышевск",
      "Первомайский",
      "Дарасун"
    ],
    "kamchatskiy-kray": [
      "Петропавловск-Камчатский",
      "Елизово",
      "Вилючинск",
      "Мильково",
      "Ключи",
      "Усть-Камчатск",
      "Палана",
      "Тигиль",
      "Эссо",
      "Соболево",
      "Усть-Большерецк",
      "Никольское",
      "Оссора",
      "Коряки",
      "Раздольный",
      "Пионерский"
    ],
    "primorskiy-kray": [
      "Владивосток",
      "Уссурийск",
      "Находка",
      "Артём",
      "Арсеньев",
      "Спасск-Дальний",
      "Большой Камень",
      "Партизанск",
      "Лесозаводск",
      "Дальнегорск",
      "Дальнереченск",
      "Фокино",
      "Лучегорск",
      "Кавалерово",
      "Чугуевка",
      "Славянка"
    ],
    "habarovskiy-kray": [
      "Хабаровск",
      "Комсомольск-на-Амуре",
      "Амурск",
      "Советская Гавань",
      "Николаевск-на-Амуре",
      "Бикин",
      "Вяземский",
      "Ванино",
      "Чегдомын",
      "Солнечный",
      "Эльбан",
      "Хор",
      "Переяславка",
      "Охотск",
      "Аян",
      "Троицкое"
    ],
    "amurskaya-oblast": [
      "Благовещенск",
      "Белогорск",
      "Свободный",
      "Тында",
      "Зея",
      "Райчихинск",
      "Шимановск",
      "Сковородино",
      "Завитинск",
      "Циолковский",
      "Прогресс",
      "Серышево",
      "Екатеринославка",
      "Ивановка",
      "Тамбовка",
      "Архара"
    ],
    "magadanskaya-oblast": [
      "Магадан",
      "Сокол",
      "Ола",
      "Палатка",
      "Сусуман",
      "Ягодное",
      "Омсукчан",
      "Сеймчан",
      "Усть-Омчуг",
      "Дукат",
      "Хасын",
      "Атка",
      "Синегорье",
      "Стекольный",
      "Талая",
      "Мяунджа"
    ],
    "sahalinskaya-oblast": [
      "Южно-Сахалинск",
      "Корсаков",
      "Холмск",
      "Оха",
      "Поронайск",
      "Долинск",
      "Невельск",
      "Александровск-Сахалинский",
      "Углегорск",
      "Макаров",
      "Томари",
      "Анива",
      "Ноглики",
      "Смирных",
      "Тымовское",
      "Курильск"
    ],
    "evreyskaya-avtonomnaya-oblast": [
      "Биробиджан",
      "Облучье",
      "Теплоозёрск",
      "Известковый",
      "Смидович",
      "Волочаевка-2",
      "Николаевка",
      "Ленинское",
      "Амурзет",
      "Бира",
      "Лондоко-завод",
      "Приамурский",
      "Кульдур",
      "Пашково",
      "Бабстово",
      "Валдгейм"
    ],
    "chukotskiy-avtonomnyy-okrug": [
      "Анадырь",
      "Билибино",
      "Певек",
      "Эгвекинот",
      "Провидения",
      "Лаврентия",
      "Уэлен",
      "Лорино",
      "Рыркайпий",
      "Мыс Шмидта",
      "Угольные Копи",
      "Беринговский",
      "Омолон",
      "Энурмино",
      "Алькатваам",
      "Канчалан",
      "Марково"
    ]
  }
}
