{
  "version": "v58",
  "build": "release-coherence-legal-domain-ready",
  "date": "2026-04-26",
  "status": "single full release package; deploy/version pages synchronized; public 10-region layer rechecked",
  "regions": 10,
  "subregions": 42,
  "region_crop_guides": 120,
  "expected_checks": [
    "V58_DEPLOY_TEST.txt",
    "version.html",
    "deployment-check.html",
    "data/site-version.json",
    "index.html",
    "regions.html",
    "purchase.html",
    "soil.html",
    "calendar.html",
    "first-garden.html",
    "do-not-buy.html",
    "garden-health-check.html",
    "contacts.html",
    "privacy.html",
    "terms.html",
    "launch-checklist.html",
    "legal-checklist.html",
    "sitemap.xml",
    "robots.txt"
  ],
  "notes": [
    "Собрана полноценная v58 без точечных hotfix-пакетов: один архив для чистого наката.",
    "Служебные страницы version.html и deployment-check.html синхронизированы с v58.",
    "Старые deploy-маркеры V54–V57 удалены из архива v58, чтобы не путать проверку.",
    "Публичные обзорные страницы покупки, почвы, календаря, первого сада и антисписка проверены на 10 регионов.",
    "Контактные и юридические страницы оставлены без выдуманных реквизитов: перед доменом нужно подставить реальные канал связи, владельца проекта и набор подключённых сервисов.",
    "После деплоя проверяйте /V58_DEPLOY_TEST.txt, /data/site-version.json, /version.html, /deployment-check.html, /purchase.html и /soil.html."
  ]
}
